vicentin/__init__.py
vicentin/data_structures/__init__.py
vicentin/data_structures/graph.py
vicentin/data_structures/heap.py
vicentin/data_structures/priority_queue.py
vicentin/data_structures/queue.py
vicentin/data_structures/stack.py
vicentin/data_structures/tree.py
vicentin/data_structures/trie.py
vicentin/data_structures/union_find.py
vicentin/dp/__init__.py
vicentin/dp/knapsack.py
vicentin/dp/matrix_multiplication.py
vicentin/dp/rod_cut.py
vicentin/dp/str/__init__.py
vicentin/dp/str/edit_distance.py
vicentin/graph/mst.py
vicentin/graph/negative_cycle.py
vicentin/graph/shortest_path.py
vicentin/image/__init__.py
vicentin/image/differentiation.py
vicentin/image/img2graph.py
vicentin/image/regularization.py
vicentin/image/utils.py
vicentin/image/video/__init__.py
vicentin/image/video/optical_flow/__init__.py
vicentin/image/video/optical_flow/block_matching.py
vicentin/image/video/optical_flow/horn_schunck.py
vicentin/misc/__init__.py
vicentin/misc/polynomial.py
vicentin/misc/subsequence.py
vicentin/optimization/__init__.py
vicentin/optimization/minimization/__init__.py
vicentin/optimization/minimization/barrier_method/__init__.py
vicentin/optimization/minimization/barrier_method/barrier.py
vicentin/optimization/minimization/barrier_method/barrier_np.py
vicentin/optimization/minimization/barrier_method/barrier_torch.py
vicentin/optimization/minimization/gradient_descent/__init__.py
vicentin/optimization/minimization/gradient_descent/gradient_descent.py
vicentin/optimization/minimization/gradient_descent/gradient_descent_np.py
vicentin/optimization/minimization/gradient_descent/gradient_descent_torch.py
vicentin/optimization/minimization/newton_method/__init__.py
vicentin/optimization/minimization/newton_method/newton.py
vicentin/optimization/minimization/newton_method/newton_np.py
vicentin/optimization/minimization/newton_method/newton_torch.py
vicentin/optimization/problems/__init__.py
vicentin/optimization/problems/LP/__init__.py
vicentin-0.11.dist-info/licenses/LICENSE
vicentin-0.11.dist-info/METADATA
vicentin-0.11.dist-info/WHEEL
vicentin-0.11.dist-info/top_level.txt
vicentin-0.11.dist-info/RECORD
