Metadata-Version: 2.4
Name: vicentin
Version: 0.11
Summary: Personal collection of algorithms.
Author-email: Felipe Vicentin <hello@a.vicentin.xyz>
License: MIT License
Project-URL: Homepage, https://github.com/Vinschers/algorithms
Classifier: Programming Language :: Python :: 3
Classifier: Operating System :: OS Independent
Requires-Python: <3.13,>=3.11
License-File: LICENSE
Requires-Dist: numpy
Requires-Dist: scipy
Requires-Dist: scikit-image
Requires-Dist: networkx
Dynamic: license-file
